{
  "<common-default-footer-block>": {
    "template": "./index.marko",
    "@bg-color": "string",
    "@footer-text": "object"
  },
  "<common-dss-footer-block>": {
    "template": "./dss.marko"
  },
  "<common-sso-footer-block>": {
    "template": "./sso.marko",
    "@newsletter": "object",
    "@primary-color": "string"
  },
  "<common-gip-footer-block>": {
    "template": "./gip.marko"
  },
  "<common-fcp-footer-block>": {
    "template": "./fcp.marko",
    "@newsletter": "object",
    "@primary-color": "string"
  },
  "<common-footer-block>": {
    "template": "./footer.marko",
    "@newsletter": "object",
    "@primary-color": "string",
    "@company": "string"
  },
  "<common-psc-footer-block>": {
    "template": "./psc.marko"
  }
}
